huawei_cloud_provider/__init__.py
huawei_cloud_provider/hooks/__init__.py
huawei_cloud_provider/hooks/base_huawei_cloud.py
huawei_cloud_provider/hooks/cdm.py
huawei_cloud_provider/hooks/dataarts.py
huawei_cloud_provider/hooks/dli.py
huawei_cloud_provider/hooks/dws.py
huawei_cloud_provider/hooks/huawei_obs.py
huawei_cloud_provider/hooks/modelarts.py
huawei_cloud_provider/hooks/smn.py
huawei_cloud_provider/hooks/utils/__init__.py
huawei_cloud_provider/hooks/utils/signer.py
huawei_cloud_provider/operators/__init__.py
huawei_cloud_provider/operators/cdm.py
huawei_cloud_provider/operators/dataarts.py
huawei_cloud_provider/operators/dli.py
huawei_cloud_provider/operators/dws.py
huawei_cloud_provider/operators/huawei_obs.py
huawei_cloud_provider/operators/modelarts.py
huawei_cloud_provider/operators/smn.py
huawei_cloud_provider/sensors/__init__.py
huawei_cloud_provider/sensors/cdm.py
huawei_cloud_provider/sensors/dataarts.py
huawei_cloud_provider/sensors/dli.py
huawei_cloud_provider/sensors/dws.py
huawei_cloud_provider/sensors/huawei_obs_key.py
huawei_cloud_provider/sensors/modelarts.py
airflow_provider_huawei_cloud_demo-0.0.23.dist-info/LICENSE
airflow_provider_huawei_cloud_demo-0.0.23.dist-info/METADATA
airflow_provider_huawei_cloud_demo-0.0.23.dist-info/WHEEL
airflow_provider_huawei_cloud_demo-0.0.23.dist-info/entry_points.txt
airflow_provider_huawei_cloud_demo-0.0.23.dist-info/top_level.txt
airflow_provider_huawei_cloud_demo-0.0.23.dist-info/RECORD
