Metadata-Version: 2.1
Name: airflow-provider-huawei-cloud-demo
Version: 0.0.23
Summary: Huawei Cloud integration for Apoache Airflow
Home-page: https://github.com/emincanozcan/airflow-provider-huawei-cloud
Author: Emincan Ozcan
Author-email: emincan@emincanozcan.com
Classifier: Programming Language :: Python :: 3
Classifier: License :: OSI Approved :: Apache Software License
Classifier: Operating System :: OS Independent
Requires-Python: >=3.7
License-File: LICENSE
Requires-Dist: apache-airflow (>=2.5.0)
Requires-Dist: huaweicloudsdkcore (==3.1.21)
Requires-Dist: esdk-obs-python (==3.22.2)
Requires-Dist: huaweicloudsdkdws (==3.1.21)
Requires-Dist: huaweicloudsdksmn (==3.1.19)
Requires-Dist: huaweicloudsdkdli (==3.1.19)
Requires-Dist: huaweicloudsdkcdm (==3.1.19)
Requires-Dist: huaweicloudsdkdlf (==3.1.19)
Requires-Dist: huaweicloudsdkiam (==3.1.19)
Requires-Dist: requests (==2.28.2)
